README.md
flask_statsd.py
setup.py
flask_statsd_tags.egg-info/PKG-INFO
flask_statsd_tags.egg-info/SOURCES.txt
flask_statsd_tags.egg-info/dependency_links.txt
flask_statsd_tags.egg-info/not-zip-safe
flask_statsd_tags.egg-info/requires.txt
flask_statsd_tags.egg-info/top_level.txt