Metadata-Version: 1.1
Name: flask-statsd-tags
Version: 2.0.0
Summary: Flask metrics in Influx Statsd format.
Home-page: https://github.com/gfreezy/flask-statsd/
Author: gfreezy
Author-email: gfreezy@gmail.com
License: BSD
Platform: any
Classifier: Environment :: Web Environment
Classifier: Intended Audience :: Developers
Classifier: License :: OSI Approved :: BSD License
Classifier: Operating System :: OS Independent
Classifier: Programming Language :: Python
Classifier: Topic :: Internet :: WWW/HTTP :: Dynamic Content
Classifier: Topic :: Software Development :: Libraries :: Python Modules
